[{"__symbolic":"module","version":4,"metadata":{"AppFooterComponent":{"__symbolic":"class","decorators":[{"__symbolic":"call","expression":{"__symbolic":"reference","module":"@angular/core","name":"Component","line":3,"character":1},"arguments":[{"selector":"app-footer","template":"\n    <footer class=\"app-footer\">\n      <ng-content></ng-content>\n    </footer>\n  "}]}],"members":{"fixed":[{"__symbolic":"property","decorators":[{"__symbolic":"call","expression":{"__symbolic":"reference","module":"@angular/core","name":"Input","line":12,"character":3}}]}],"__ctor__":[{"__symbolic":"constructor","parameters":[{"__symbolic":"reference","module":"@angular/core","name":"ElementRef","line":14,"character":26}]}],"ngOnInit":[{"__symbolic":"method"}],"isFixed":[{"__symbolic":"method"}]}}}}]